pyedo/__init__.py
pyedo/_info.py
pyedo/edo.py
pyedo/examples/StartUp.py
pyedo/examples/move_cartesianX.py
pyedo/examples/prog_cartesian.py
pyedo/examples/prog_circular.py
pyedo/examples/prog_circularX.py
pyedo/examples/prog_jogjoint.py
pyedo/examples/rodeo.py
pyedo-0.7.dist-info/LICENSE
pyedo-0.7.dist-info/METADATA
pyedo-0.7.dist-info/WHEEL
pyedo-0.7.dist-info/top_level.txt
pyedo-0.7.dist-info/RECORD
